run_gui.py
cli/__init__.py
cli/aes_cli.py
core/__init__.py
core/aes_crypto.py
core/batch_encrypt.py
core/key_store.py
gui/__init__.py
gui/file_tab.py
gui/folder_tab.py
gui/keys_tab.py
gui/main_window.py
gui/settings_dialog.py
utils/__init__.py
utils/logger.py
fence_file_encryption_engine-0.1.7.dist-info/LICENSE
fence_file_encryption_engine-0.1.7.dist-info/METADATA
fence_file_encryption_engine-0.1.7.dist-info/WHEEL
fence_file_encryption_engine-0.1.7.dist-info/entry_points.txt
fence_file_encryption_engine-0.1.7.dist-info/top_level.txt
fence_file_encryption_engine-0.1.7.dist-info/RECORD
