Metadata-Version: 2.2
Name: fence-file-encryption-engine
Version: 0.1.7
Summary: AES file/folder encryption tool with CLI and Tkinter GUI
Author: Kushagra Bhardwaj
License: MIT
Project-URL: Homepage, https://github.com/bhardwaj-kushagra/FENCE
Project-URL: Repository, https://github.com/bhardwaj-kushagra/FENCE
Project-URL: Issues, https://github.com/bhardwaj-kushagra/FENCE/issues
Project-URL: Changelog, https://github.com/bhardwaj-kushagra/FENCE/blob/main/CHANGES.md
Project-URL: Documentation, https://github.com/bhardwaj-kushagra/FENCE/blob/main/DOCS/DOCUMENTATION.md
Keywords: aes,encryption,cryptography,cli,gui,file-encryption
Classifier: Development Status :: 4 - Beta
Classifier: Intended Audience :: Developers
Classifier: License :: OSI Approved :: MIT License
Classifier: Programming Language :: Python
Classifier: Programming Language :: Python :: 3
Classifier: Programming Language :: Python :: 3.8
Classifier: Programming Language :: Python :: 3.9
Classifier: Programming Language :: Python :: 3.10
Classifier: Programming Language :: Python :: 3.11
Classifier: Programming Language :: Python :: 3.12
Classifier: Environment :: Console
Classifier: Topic :: Security :: Cryptography
Requires-Python: >=3.8
License-File: LICENSE
Requires-Dist: pycryptodome>=3.18.0
Requires-Dist: rich>=13.0.0
Provides-Extra: dev
Requires-Dist: pytest>=7.4.0; extra == "dev"
Requires-Dist: build>=1.2.2; extra == "dev"
Requires-Dist: twine>=5.0.0; extra == "dev"
